CHANGELOG.md
CONTRIBUTORS
LICENSE
MANIFEST.in
README.md
setup.py
knox/__init__.py
knox/admin.py
knox/auth.py
knox/const.py
knox/crypto.py
knox/models.py
knox/serializers.py
knox/settings.py
knox/signals.py
knox/urls.py
knox/views.py
knox/migrations/0001_initial.py
knox/migrations/0002_auto_20150916_1425.py
knox/migrations/0003_auto_20150916_1526.py
knox/migrations/0004_authtoken_expires.py
knox/migrations/0005_authtoken_token_key.py
knox/migrations/0006_auto_20160818_0932.py
knox/migrations/0007_auto_20190111_0542.py
knox/migrations/0008_remove_authtoken_salt.py
knox/migrations/0009_authtoken_token_type.py
knox/migrations/0010_alter_authtoken_token_type.py
knox/migrations/0011_alter_authtoken_token_type.py
knox/migrations/__init__.py
qube_money_knox.egg-info/PKG-INFO
qube_money_knox.egg-info/SOURCES.txt
qube_money_knox.egg-info/dependency_links.txt
qube_money_knox.egg-info/requires.txt
qube_money_knox.egg-info/top_level.txt
tests/tests.py