Metadata-Version: 2.1
Name: qube-money-knox
Version: 4.2.7
Summary: Custom Fork of django-rest-knox
Home-page: https://github.com/qubemoney/django-rest-knox
Author: Qube Money
Author-email: admin@qubemoney.com
License: MIT
Keywords: django rest authentication login
Classifier: Development Status :: 5 - Production/Stable
Classifier: Intended Audience :: Developers
Classifier: Topic :: Internet :: WWW/HTTP :: Session
Classifier: License :: OSI Approved :: MIT License
Classifier: Programming Language :: Python :: 3
Classifier: Programming Language :: Python :: 3.7
Classifier: Programming Language :: Python :: 3.8
Classifier: Programming Language :: Python :: 3.9
Classifier: Programming Language :: Python :: 3.10
Requires-Python: >=3.6
Provides-Extra: dev
Provides-Extra: test
License-File: LICENSE
